{
  "id": "art_1780054200699",
  "slug": "java-polymorphism",
  "title": "Javaの多態性",
  "summary": "Javaの多態性は、オブジェクト指向プログラミングの重要な概念の一つです。多態性を使用すると、同じメソッド名で異なる動作を実行することができます。この記事では、多態性の基本とその使用方法について説明します。",
  "body": "<h2>多態性とは</h2><p>多態性は、オブジェクト指向プログラミングの重要な概念の一つです。多態性を使用すると、同じメソッド名で異なる動作を実行することができます。</p><h3>多態性の種類</h3><p>Javaでは、多態性には2種類あります。1つは、オーバーロードと呼ばれるもので、同じメソッド名で異なる引数を取ることができます。もう1つは、オーバーライドと呼ばれるもので、親クラスと子クラスで同じメソッド名を使用します。</p><h3>多態性の使用方法</h3><p>多態性を使用するには、まず親クラスと子クラスを定義します。次に、親クラスにメソッドを定義し、子クラスでそのメソッドをオーバーライドします。最後に、子クラスのインスタンスを生成し、オーバーライドされたメソッドを呼び出します。</p><pre><code>public class Animal {<br>    public void sound() {<br>        System.out.println(\"動物が音を出す\");<br>    }<br>}<br><br>public class Dog extends Animal {<br>    @Override<br>    public void sound() {<br>        System.out.println(\"犬が吠える\");<br>    }<br>}<br><br>public class Main {<br>    public static void main(String[] args) {<br>        Animal animal = new Dog();<br>        animal.sound();<br>    }<br>}<br></code></pre>",
  "conclusion": "この記事では、Javaの多態性について説明しました。多態性は、オブジェクト指向プログラミングの重要な概念の一つであり、同じメソッド名で異なる動作を実行することができます。多態性を使用するには、親クラスと子クラスを定義し、メソッドをオーバーライドする必要があります。次回は、例外処理について説明します。",
  "tags": [
    "Java",
    "多態性",
    "オブジェクト指向プログラミング"
  ],
  "category": "Java",
  "theme": "java - Java",
  "status": "published",
  "createdAt": "2026-05-29T11:30:00.683Z",
  "updatedAt": "2026-05-30T05:00:58.626Z",
  "publishedAt": "2026-05-29T11:30:00.683Z",
  "metaTitle": "Javaの多態性｜Java入門 | StackShelf",
  "metaDescription": "【Java初心者向け】Javaの多態性は、オブジェクト指向プログラミングの重要な概念の一つです。この記事では、多態性の基本とその使用方法について説明します。 図解・具体例つきで丁寧に解説します。",
  "ogTitle": "Javaの多態性",
  "ogDescription": "【Java初心者向け】Javaの多態性は、オブジェクト指向プログラミングの重要な概念の一つです。この記事では、多態性の基本とその使用方法について説明します。 図解・具体例つきで丁寧に解説します。",
  "knowledge": {
    "topic": "java",
    "courseId": "java",
    "episode": 10
  },
  "faq": [
    {
      "question": "多態性とは何ですか？",
      "answer": "多態性は、同じメソッド名で異なる動作を実行することができるオブジェクト指向プログラミングの概念です。"
    },
    {
      "question": "多態性には何種類ありますか？",
      "answer": "多態性には、オーバーロードとオーバーライドの2種類があります。"
    },
    {
      "question": "多態性を使用するには何をする必要がありますか？",
      "answer": "多態性を使用するには、親クラスと子クラスを定義し、メソッドをオーバーライドする必要があります。"
    },
    {
      "question": "Javaを学ぶのに数学は必要ですか？",
      "answer": "基礎レベルでは四則演算程度で十分です。オブジェクト指向の考え方に慣れることが最初のハードルで、高度な数学は後から必要になる場面もあります。"
    },
    {
      "question": "コンパイルエラーと実行時エラーの違いは？",
      "answer": "コンパイルエラーはプログラムを実行する前に文法や型の問題で検出されます。実行時エラーは動かしてから初めて表面化する問題（NullPointerException など）です。"
    }
  ],
  "nextEpisodeHint": "次回は、例外処理について説明します。",
  "canonical": "https://ai-site-iota-nine.vercel.app/article/java-polymorphism",
  "jsonLd": {
    "@context": "https://schema.org",
    "@graph": [
      {
        "@context": "https://schema.org",
        "@type": "TechArticle",
        "headline": "Javaの多態性",
        "description": "【Java初心者向け】Javaの多態性は、オブジェクト指向プログラミングの重要な概念の一つです。この記事では、多態性の基本とその使用方法について説明します。 図解・具体例つきで丁寧に解説します。",
        "datePublished": "2026-05-29T11:30:00.683Z",
        "dateModified": "2026-05-30T05:00:58.626Z",
        "author": {
          "@type": "Organization",
          "name": "StackShelf",
          "url": "https://ai-site-iota-nine.vercel.app",
          "logo": {
            "@type": "ImageObject",
            "url": "https://ai-site-iota-nine.vercel.app/favicon.svg"
          }
        },
        "publisher": {
          "@type": "Organization",
          "name": "StackShelf",
          "url": "https://ai-site-iota-nine.vercel.app",
          "logo": {
            "@type": "ImageObject",
            "url": "https://ai-site-iota-nine.vercel.app/favicon.svg"
          }
        },
        "image": "https://ai-site-iota-nine.vercel.app/og-default.svg",
        "inLanguage": "ja",
        "wordCount": 551,
        "mainEntityOfPage": {
          "@type": "WebPage",
          "@id": "https://ai-site-iota-nine.vercel.app/article/java-polymorphism"
        },
        "keywords": "Java, 多態性, オブジェクト指向プログラミング",
        "articleSection": "Java",
        "url": "https://ai-site-iota-nine.vercel.app/article/java-polymorphism",
        "learningResourceType": "tutorial",
        "educationalLevel": "beginner"
      },
      {
        "@context": "https://schema.org",
        "@type": "BreadcrumbList",
        "itemListElement": [
          {
            "@type": "ListItem",
            "position": 1,
            "name": "ホーム",
            "item": "https://ai-site-iota-nine.vercel.app/"
          },
          {
            "@type": "ListItem",
            "position": 2,
            "name": "java",
            "item": "https://ai-site-iota-nine.vercel.app/knowledge/java"
          },
          {
            "@type": "ListItem",
            "position": 3,
            "name": "Java",
            "item": "https://ai-site-iota-nine.vercel.app/course/java/java"
          },
          {
            "@type": "ListItem",
            "position": 4,
            "name": "Javaの多態性",
            "item": "https://ai-site-iota-nine.vercel.app/article/java-polymorphism"
          }
        ]
      },
      {
        "@context": "https://schema.org",
        "@type": "Course",
        "name": "Java",
        "description": "Javaプログラミング言語の基礎から応用までを学習する講座です。初心者向けにJavaの基本構文、オブジェクト指向、データ構造、アルゴリズムなどを解説します。",
        "provider": {
          "@type": "Organization",
          "name": "StackShelf",
          "url": "https://ai-site-iota-nine.vercel.app"
        },
        "url": "https://ai-site-iota-nine.vercel.app/course/java/java",
        "inLanguage": "ja",
        "educationalLevel": "beginner",
        "hasCourseInstance": {
          "@type": "CourseInstance",
          "courseMode": "online",
          "courseWorkload": "PT1H"
        }
      },
      {
        "@context": "https://schema.org",
        "@type": "FAQPage",
        "mainEntity": [
          {
            "@type": "Question",
            "name": "多態性とは何ですか？",
            "acceptedAnswer": {
              "@type": "Answer",
              "text": "多態性は、同じメソッド名で異なる動作を実行することができるオブジェクト指向プログラミングの概念です。"
            }
          },
          {
            "@type": "Question",
            "name": "多態性には何種類ありますか？",
            "acceptedAnswer": {
              "@type": "Answer",
              "text": "多態性には、オーバーロードとオーバーライドの2種類があります。"
            }
          },
          {
            "@type": "Question",
            "name": "多態性を使用するには何をする必要がありますか？",
            "acceptedAnswer": {
              "@type": "Answer",
              "text": "多態性を使用するには、親クラスと子クラスを定義し、メソッドをオーバーライドする必要があります。"
            }
          },
          {
            "@type": "Question",
            "name": "Javaを学ぶのに数学は必要ですか？",
            "acceptedAnswer": {
              "@type": "Answer",
              "text": "基礎レベルでは四則演算程度で十分です。オブジェクト指向の考え方に慣れることが最初のハードルで、高度な数学は後から必要になる場面もあります。"
            }
          },
          {
            "@type": "Question",
            "name": "コンパイルエラーと実行時エラーの違いは？",
            "acceptedAnswer": {
              "@type": "Answer",
              "text": "コンパイルエラーはプログラムを実行する前に文法や型の問題で検出されます。実行時エラーは動かしてから初めて表面化する問題（NullPointerException など）です。"
            }
          }
        ]
      }
    ]
  },
  "breadcrumb": {
    "@context": "https://schema.org",
    "@type": "BreadcrumbList",
    "itemListElement": [
      {
        "@type": "ListItem",
        "position": 1,
        "name": "ホーム",
        "item": "https://ai-site-iota-nine.vercel.app/"
      },
      {
        "@type": "ListItem",
        "position": 2,
        "name": "java",
        "item": "https://ai-site-iota-nine.vercel.app/knowledge/java"
      },
      {
        "@type": "ListItem",
        "position": 3,
        "name": "Java",
        "item": "https://ai-site-iota-nine.vercel.app/course/java/java"
      },
      {
        "@type": "ListItem",
        "position": 4,
        "name": "Javaの多態性",
        "item": "https://ai-site-iota-nine.vercel.app/article/java-polymorphism"
      }
    ]
  },
  "courseSchema": {
    "@context": "https://schema.org",
    "@type": "Course",
    "name": "Java",
    "description": "Javaプログラミング言語の基礎から応用までを学習する講座です。初心者向けにJavaの基本構文、オブジェクト指向、データ構造、アルゴリズムなどを解説します。",
    "provider": {
      "@type": "Organization",
      "name": "StackShelf",
      "url": "https://ai-site-iota-nine.vercel.app"
    },
    "url": "https://ai-site-iota-nine.vercel.app/course/java/java",
    "inLanguage": "ja",
    "educationalLevel": "beginner",
    "hasCourseInstance": {
      "@type": "CourseInstance",
      "courseMode": "online",
      "courseWorkload": "PT1H"
    }
  },
  "faqSchema": {
    "@context": "https://schema.org",
    "@type": "FAQPage",
    "mainEntity": [
      {
        "@type": "Question",
        "name": "多態性とは何ですか？",
        "acceptedAnswer": {
          "@type": "Answer",
          "text": "多態性は、同じメソッド名で異なる動作を実行することができるオブジェクト指向プログラミングの概念です。"
        }
      },
      {
        "@type": "Question",
        "name": "多態性には何種類ありますか？",
        "acceptedAnswer": {
          "@type": "Answer",
          "text": "多態性には、オーバーロードとオーバーライドの2種類があります。"
        }
      },
      {
        "@type": "Question",
        "name": "多態性を使用するには何をする必要がありますか？",
        "acceptedAnswer": {
          "@type": "Answer",
          "text": "多態性を使用するには、親クラスと子クラスを定義し、メソッドをオーバーライドする必要があります。"
        }
      },
      {
        "@type": "Question",
        "name": "Javaを学ぶのに数学は必要ですか？",
        "acceptedAnswer": {
          "@type": "Answer",
          "text": "基礎レベルでは四則演算程度で十分です。オブジェクト指向の考え方に慣れることが最初のハードルで、高度な数学は後から必要になる場面もあります。"
        }
      },
      {
        "@type": "Question",
        "name": "コンパイルエラーと実行時エラーの違いは？",
        "acceptedAnswer": {
          "@type": "Answer",
          "text": "コンパイルエラーはプログラムを実行する前に文法や型の問題で検出されます。実行時エラーは動かしてから初めて表面化する問題（NullPointerException など）です。"
        }
      }
    ]
  },
  "internalLinkCandidates": [
    {
      "slug": "java-classes",
      "title": "Javaのクラスとオブジェクト",
      "reason": "同じ講座の関連回です"
    },
    {
      "slug": "java-objects",
      "title": "Javaのオブジェクト指向プログラミング",
      "reason": "同じ講座の関連回です"
    },
    {
      "slug": "java-exception-handling",
      "title": "Javaの例外処理",
      "reason": "同じ講座の関連回です"
    },
    {
      "slug": "java-inheritance",
      "title": "Javaの継承",
      "reason": "同じ講座の関連回です"
    },
    {
      "slug": "java-arrays",
      "title": "Javaの配列",
      "reason": "同じ講座の関連回です"
    }
  ],
  "nextAction": "次は例外処理について説明します。",
  "ogImage": "https://ai-site-iota-nine.vercel.app/og-default.svg"
}